<?xml version="1.0" encoding="utf-8" standalone="yes"?>
<Gesture Name = "s">
	<Stroke>
		<Point X = "310" Y = "-292" T = "0" Pressure = "0" />
		<Point X = "310" Y = "-292" T = "0" Pressure = "0" />
		<Point X = "310" Y = "-292" T = "0" Pressure = "0" />
		<Point X = "310" Y = "-292" T = "0" Pressure = "0" />
		<Point X = "310" Y = "-292" T = "0" Pressure = "0" />
		<Point X = "310" Y = "-292" T = "0" Pressure = "0" />
		<Point X = "310" Y = "-292" T = "0" Pressure = "0" />
		<Point X = "310" Y = "-292" T = "0" Pressure = "0" />
		<Point X = "310" Y = "-292" T = "0" Pressure = "0" />
		<Point X = "310" Y = "-292" T = "0" Pressure = "0" />
		<Point X = "310" Y = "-292" T = "0" Pressure = "0" />
		<Point X = "310" Y = "-292" T = "0" Pressure = "0" />
		<Point X = "310" Y = "-292" T = "0" Pressure = "0" />
		<Point X = "310" Y = "-292" T = "0" Pressure = "0" />
		<Point X = "310" Y = "-293" T = "0" Pressure = "0" />
		<Point X = "310" Y = "-293" T = "0" Pressure = "0" />
		<Point X = "310" Y = "-293" T = "0" Pressure = "0" />
		<Point X = "310" Y = "-293" T = "0" Pressure = "0" />
		<Point X = "309" Y = "-293" T = "0" Pressure = "0" />
		<Point X = "309" Y = "-293" T = "0" Pressure = "0" />
		<Point X = "309" Y = "-293" T = "0" Pressure = "0" />
		<Point X = "309" Y = "-293" T = "0" Pressure = "0" />
		<Point X = "308" Y = "-293" T = "0" Pressure = "0" />
		<Point X = "308" Y = "-293" T = "0" Pressure = "0" />
		<Point X = "308" Y = "-293" T = "0" Pressure = "0" />
		<Point X = "307" Y = "-293" T = "0" Pressure = "0" />
		<Point X = "307" Y = "-293" T = "0" Pressure = "0" />
		<Point X = "307" Y = "-293" T = "0" Pressure = "0" />
		<Point X = "306" Y = "-293" T = "0" Pressure = "0" />
		<Point X = "306" Y = "-293" T = "0" Pressure = "0" />
		<Point X = "305" Y = "-293" T = "0" Pressure = "0" />
		<Point X = "305" Y = "-293" T = "0" Pressure = "0" />
		<Point X = "305" Y = "-293" T = "0" Pressure = "0" />
		<Point X = "304" Y = "-293" T = "0" Pressure = "0" />
		<Point X = "304" Y = "-293" T = "0" Pressure = "0" />
		<Point X = "303" Y = "-293" T = "0" Pressure = "0" />
		<Point X = "303" Y = "-293" T = "0" Pressure = "0" />
		<Point X = "303" Y = "-293" T = "0" Pressure = "0" />
		<Point X = "302" Y = "-293" T = "0" Pressure = "0" />
		<Point X = "301" Y = "-293" T = "0" Pressure = "0" />
		<Point X = "301" Y = "-293" T = "0" Pressure = "0" />
		<Point X = "301" Y = "-293" T = "0" Pressure = "0" />
		<Point X = "300" Y = "-293" T = "0" Pressure = "0" />
		<Point X = "300" Y = "-293" T = "0" Pressure = "0" />
		<Point X = "300" Y = "-293" T = "0" Pressure = "0" />
		<Point X = "299" Y = "-293" T = "0" Pressure = "0" />
		<Point X = "299" Y = "-293" T = "0" Pressure = "0" />
		<Point X = "299" Y = "-293" T = "0" Pressure = "0" />
		<Point X = "298" Y = "-293" T = "0" Pressure = "0" />
		<Point X = "297" Y = "-293" T = "0" Pressure = "0" />
		<Point X = "297" Y = "-293" T = "0" Pressure = "0" />
		<Point X = "297" Y = "-293" T = "0" Pressure = "0" />
		<Point X = "296" Y = "-293" T = "0" Pressure = "0" />
		<Point X = "296" Y = "-293" T = "0" Pressure = "0" />
		<Point X = "295" Y = "-293" T = "0" Pressure = "0" />
		<Point X = "294" Y = "-293" T = "0" Pressure = "0" />
		<Point X = "293" Y = "-293" T = "0" Pressure = "0" />
		<Point X = "292" Y = "-293" T = "0" Pressure = "0" />
		<Point X = "291" Y = "-293" T = "0" Pressure = "0" />
		<Point X = "290" Y = "-293" T = "0" Pressure = "0" />
		<Point X = "289" Y = "-292" T = "0" Pressure = "0" />
		<Point X = "288" Y = "-292" T = "0" Pressure = "0" />
		<Point X = "286" Y = "-291" T = "0" Pressure = "0" />
		<Point X = "286" Y = "-291" T = "0" Pressure = "0" />
		<Point X = "284" Y = "-291" T = "0" Pressure = "0" />
		<Point X = "283" Y = "-290" T = "0" Pressure = "0" />
		<Point X = "282" Y = "-290" T = "0" Pressure = "0" />
		<Point X = "282" Y = "-290" T = "0" Pressure = "0" />
		<Point X = "280" Y = "-290" T = "0" Pressure = "0" />
		<Point X = "280" Y = "-289" T = "0" Pressure = "0" />
		<Point X = "279" Y = "-289" T = "0" Pressure = "0" />
		<Point X = "279" Y = "-289" T = "0" Pressure = "0" />
		<Point X = "278" Y = "-289" T = "0" Pressure = "0" />
		<Point X = "278" Y = "-289" T = "0" Pressure = "0" />
		<Point X = "277" Y = "-289" T = "0" Pressure = "0" />
		<Point X = "276" Y = "-288" T = "0" Pressure = "0" />
		<Point X = "276" Y = "-288" T = "0" Pressure = "0" />
		<Point X = "276" Y = "-288" T = "0" Pressure = "0" />
		<Point X = "275" Y = "-287" T = "0" Pressure = "0" />
		<Point X = "275" Y = "-287" T = "0" Pressure = "0" />
		<Point X = "275" Y = "-287" T = "0" Pressure = "0" />
		<Point X = "274" Y = "-287" T = "0" Pressure = "0" />
		<Point X = "274" Y = "-287" T = "0" Pressure = "0" />
		<Point X = "273" Y = "-286" T = "0" Pressure = "0" />
		<Point X = "272" Y = "-286" T = "0" Pressure = "0" />
		<Point X = "272" Y = "-286" T = "0" Pressure = "0" />
		<Point X = "272" Y = "-286" T = "0" Pressure = "0" />
		<Point X = "271" Y = "-285" T = "0" Pressure = "0" />
		<Point X = "270" Y = "-285" T = "0" Pressure = "0" />
		<Point X = "269" Y = "-284" T = "0" Pressure = "0" />
		<Point X = "268" Y = "-284" T = "0" Pressure = "0" />
		<Point X = "268" Y = "-283" T = "0" Pressure = "0" />
		<Point X = "267" Y = "-283" T = "0" Pressure = "0" />
		<Point X = "267" Y = "-283" T = "0" Pressure = "0" />
		<Point X = "266" Y = "-282" T = "0" Pressure = "0" />
		<Point X = "265" Y = "-282" T = "0" Pressure = "0" />
		<Point X = "264" Y = "-281" T = "0" Pressure = "0" />
		<Point X = "264" Y = "-281" T = "0" Pressure = "0" />
		<Point X = "263" Y = "-281" T = "0" Pressure = "0" />
		<Point X = "263" Y = "-280" T = "0" Pressure = "0" />
		<Point X = "263" Y = "-279" T = "0" Pressure = "0" />
		<Point X = "262" Y = "-279" T = "0" Pressure = "0" />
		<Point X = "262" Y = "-279" T = "0" Pressure = "0" />
		<Point X = "261" Y = "-278" T = "0" Pressure = "0" />
		<Point X = "260" Y = "-278" T = "0" Pressure = "0" />
		<Point X = "260" Y = "-278" T = "0" Pressure = "0" />
		<Point X = "260" Y = "-277" T = "0" Pressure = "0" />
		<Point X = "259" Y = "-277" T = "0" Pressure = "0" />
		<Point X = "259" Y = "-277" T = "0" Pressure = "0" />
		<Point X = "259" Y = "-276" T = "0" Pressure = "0" />
		<Point X = "258" Y = "-275" T = "0" Pressure = "0" />
		<Point X = "258" Y = "-275" T = "0" Pressure = "0" />
		<Point X = "257" Y = "-274" T = "0" Pressure = "0" />
		<Point X = "257" Y = "-274" T = "0" Pressure = "0" />
		<Point X = "256" Y = "-273" T = "0" Pressure = "0" />
		<Point X = "255" Y = "-273" T = "0" Pressure = "0" />
		<Point X = "255" Y = "-272" T = "0" Pressure = "0" />
		<Point X = "254" Y = "-272" T = "0" Pressure = "0" />
		<Point X = "254" Y = "-271" T = "0" Pressure = "0" />
		<Point X = "253" Y = "-270" T = "0" Pressure = "0" />
		<Point X = "253" Y = "-269" T = "0" Pressure = "0" />
		<Point X = "252" Y = "-269" T = "0" Pressure = "0" />
		<Point X = "251" Y = "-268" T = "0" Pressure = "0" />
		<Point X = "251" Y = "-267" T = "0" Pressure = "0" />
		<Point X = "250" Y = "-266" T = "0" Pressure = "0" />
		<Point X = "250" Y = "-266" T = "0" Pressure = "0" />
		<Point X = "250" Y = "-265" T = "0" Pressure = "0" />
		<Point X = "249" Y = "-264" T = "0" Pressure = "0" />
		<Point X = "249" Y = "-264" T = "0" Pressure = "0" />
		<Point X = "249" Y = "-263" T = "0" Pressure = "0" />
		<Point X = "249" Y = "-262" T = "0" Pressure = "0" />
		<Point X = "248" Y = "-261" T = "0" Pressure = "0" />
		<Point X = "248" Y = "-261" T = "0" Pressure = "0" />
		<Point X = "248" Y = "-260" T = "0" Pressure = "0" />
		<Point X = "248" Y = "-260" T = "0" Pressure = "0" />
		<Point X = "247" Y = "-259" T = "0" Pressure = "0" />
		<Point X = "247" Y = "-258" T = "0" Pressure = "0" />
		<Point X = "247" Y = "-258" T = "0" Pressure = "0" />
		<Point X = "247" Y = "-257" T = "0" Pressure = "0" />
		<Point X = "247" Y = "-257" T = "0" Pressure = "0" />
		<Point X = "247" Y = "-256" T = "0" Pressure = "0" />
		<Point X = "247" Y = "-255" T = "0" Pressure = "0" />
		<Point X = "247" Y = "-254" T = "0" Pressure = "0" />
		<Point X = "247" Y = "-253" T = "0" Pressure = "0" />
		<Point X = "247" Y = "-253" T = "0" Pressure = "0" />
		<Point X = "247" Y = "-252" T = "0" Pressure = "0" />
		<Point X = "247" Y = "-251" T = "0" Pressure = "0" />
		<Point X = "247" Y = "-250" T = "0" Pressure = "0" />
		<Point X = "247" Y = "-249" T = "0" Pressure = "0" />
		<Point X = "247" Y = "-248" T = "0" Pressure = "0" />
		<Point X = "247" Y = "-247" T = "0" Pressure = "0" />
		<Point X = "247" Y = "-246" T = "0" Pressure = "0" />
		<Point X = "248" Y = "-245" T = "0" Pressure = "0" />
		<Point X = "248" Y = "-244" T = "0" Pressure = "0" />
		<Point X = "248" Y = "-243" T = "0" Pressure = "0" />
		<Point X = "248" Y = "-243" T = "0" Pressure = "0" />
		<Point X = "248" Y = "-241" T = "0" Pressure = "0" />
		<Point X = "249" Y = "-240" T = "0" Pressure = "0" />
		<Point X = "249" Y = "-239" T = "0" Pressure = "0" />
		<Point X = "249" Y = "-239" T = "0" Pressure = "0" />
		<Point X = "250" Y = "-237" T = "0" Pressure = "0" />
		<Point X = "250" Y = "-236" T = "0" Pressure = "0" />
		<Point X = "250" Y = "-236" T = "0" Pressure = "0" />
		<Point X = "250" Y = "-235" T = "0" Pressure = "0" />
		<Point X = "251" Y = "-234" T = "0" Pressure = "0" />
		<Point X = "252" Y = "-233" T = "0" Pressure = "0" />
		<Point X = "252" Y = "-233" T = "0" Pressure = "0" />
		<Point X = "252" Y = "-232" T = "0" Pressure = "0" />
		<Point X = "253" Y = "-231" T = "0" Pressure = "0" />
		<Point X = "253" Y = "-231" T = "0" Pressure = "0" />
		<Point X = "253" Y = "-230" T = "0" Pressure = "0" />
		<Point X = "254" Y = "-229" T = "0" Pressure = "0" />
		<Point X = "254" Y = "-228" T = "0" Pressure = "0" />
		<Point X = "255" Y = "-227" T = "0" Pressure = "0" />
		<Point X = "256" Y = "-227" T = "0" Pressure = "0" />
		<Point X = "257" Y = "-225" T = "0" Pressure = "0" />
		<Point X = "257" Y = "-225" T = "0" Pressure = "0" />
		<Point X = "258" Y = "-224" T = "0" Pressure = "0" />
		<Point X = "259" Y = "-223" T = "0" Pressure = "0" />
		<Point X = "259" Y = "-222" T = "0" Pressure = "0" />
		<Point X = "261" Y = "-221" T = "0" Pressure = "0" />
		<Point X = "262" Y = "-220" T = "0" Pressure = "0" />
		<Point X = "262" Y = "-220" T = "0" Pressure = "0" />
		<Point X = "263" Y = "-219" T = "0" Pressure = "0" />
		<Point X = "264" Y = "-218" T = "0" Pressure = "0" />
		<Point X = "265" Y = "-217" T = "0" Pressure = "0" />
		<Point X = "266" Y = "-216" T = "0" Pressure = "0" />
		<Point X = "267" Y = "-216" T = "0" Pressure = "0" />
		<Point X = "268" Y = "-215" T = "0" Pressure = "0" />
		<Point X = "269" Y = "-215" T = "0" Pressure = "0" />
		<Point X = "270" Y = "-213" T = "0" Pressure = "0" />
		<Point X = "270" Y = "-213" T = "0" Pressure = "0" />
		<Point X = "271" Y = "-212" T = "0" Pressure = "0" />
		<Point X = "272" Y = "-212" T = "0" Pressure = "0" />
		<Point X = "273" Y = "-211" T = "0" Pressure = "0" />
		<Point X = "274" Y = "-211" T = "0" Pressure = "0" />
		<Point X = "275" Y = "-210" T = "0" Pressure = "0" />
		<Point X = "277" Y = "-209" T = "0" Pressure = "0" />
		<Point X = "278" Y = "-208" T = "0" Pressure = "0" />
		<Point X = "279" Y = "-208" T = "0" Pressure = "0" />
		<Point X = "281" Y = "-207" T = "0" Pressure = "0" />
		<Point X = "282" Y = "-206" T = "0" Pressure = "0" />
		<Point X = "284" Y = "-205" T = "0" Pressure = "0" />
		<Point X = "285" Y = "-204" T = "0" Pressure = "0" />
		<Point X = "287" Y = "-204" T = "0" Pressure = "0" />
		<Point X = "289" Y = "-203" T = "0" Pressure = "0" />
		<Point X = "290" Y = "-202" T = "0" Pressure = "0" />
		<Point X = "291" Y = "-202" T = "0" Pressure = "0" />
		<Point X = "292" Y = "-200" T = "0" Pressure = "0" />
		<Point X = "294" Y = "-200" T = "0" Pressure = "0" />
		<Point X = "295" Y = "-199" T = "0" Pressure = "0" />
		<Point X = "296" Y = "-198" T = "0" Pressure = "0" />
		<Point X = "298" Y = "-197" T = "0" Pressure = "0" />
		<Point X = "299" Y = "-196" T = "0" Pressure = "0" />
		<Point X = "301" Y = "-195" T = "0" Pressure = "0" />
		<Point X = "302" Y = "-194" T = "0" Pressure = "0" />
		<Point X = "303" Y = "-193" T = "0" Pressure = "0" />
		<Point X = "304" Y = "-192" T = "0" Pressure = "0" />
		<Point X = "306" Y = "-191" T = "0" Pressure = "0" />
		<Point X = "308" Y = "-190" T = "0" Pressure = "0" />
		<Point X = "309" Y = "-189" T = "0" Pressure = "0" />
		<Point X = "311" Y = "-188" T = "0" Pressure = "0" />
		<Point X = "312" Y = "-187" T = "0" Pressure = "0" />
		<Point X = "314" Y = "-186" T = "0" Pressure = "0" />
		<Point X = "315" Y = "-185" T = "0" Pressure = "0" />
		<Point X = "316" Y = "-184" T = "0" Pressure = "0" />
		<Point X = "318" Y = "-183" T = "0" Pressure = "0" />
		<Point X = "319" Y = "-182" T = "0" Pressure = "0" />
		<Point X = "320" Y = "-180" T = "0" Pressure = "0" />
		<Point X = "322" Y = "-179" T = "0" Pressure = "0" />
		<Point X = "323" Y = "-178" T = "0" Pressure = "0" />
		<Point X = "324" Y = "-178" T = "0" Pressure = "0" />
		<Point X = "325" Y = "-176" T = "0" Pressure = "0" />
		<Point X = "325" Y = "-175" T = "0" Pressure = "0" />
		<Point X = "327" Y = "-174" T = "0" Pressure = "0" />
		<Point X = "328" Y = "-173" T = "0" Pressure = "0" />
		<Point X = "329" Y = "-171" T = "0" Pressure = "0" />
		<Point X = "329" Y = "-170" T = "0" Pressure = "0" />
		<Point X = "330" Y = "-168" T = "0" Pressure = "0" />
		<Point X = "331" Y = "-167" T = "0" Pressure = "0" />
		<Point X = "332" Y = "-165" T = "0" Pressure = "0" />
		<Point X = "332" Y = "-164" T = "0" Pressure = "0" />
		<Point X = "333" Y = "-162" T = "0" Pressure = "0" />
		<Point X = "334" Y = "-161" T = "0" Pressure = "0" />
		<Point X = "335" Y = "-160" T = "0" Pressure = "0" />
		<Point X = "335" Y = "-159" T = "0" Pressure = "0" />
		<Point X = "336" Y = "-157" T = "0" Pressure = "0" />
		<Point X = "336" Y = "-157" T = "0" Pressure = "0" />
		<Point X = "337" Y = "-155" T = "0" Pressure = "0" />
		<Point X = "337" Y = "-154" T = "0" Pressure = "0" />
		<Point X = "338" Y = "-152" T = "0" Pressure = "0" />
		<Point X = "339" Y = "-151" T = "0" Pressure = "0" />
		<Point X = "339" Y = "-149" T = "0" Pressure = "0" />
		<Point X = "340" Y = "-148" T = "0" Pressure = "0" />
		<Point X = "340" Y = "-146" T = "0" Pressure = "0" />
		<Point X = "341" Y = "-145" T = "0" Pressure = "0" />
		<Point X = "341" Y = "-143" T = "0" Pressure = "0" />
		<Point X = "342" Y = "-141" T = "0" Pressure = "0" />
		<Point X = "343" Y = "-140" T = "0" Pressure = "0" />
		<Point X = "343" Y = "-138" T = "0" Pressure = "0" />
		<Point X = "343" Y = "-136" T = "0" Pressure = "0" />
		<Point X = "344" Y = "-134" T = "0" Pressure = "0" />
		<Point X = "344" Y = "-133" T = "0" Pressure = "0" />
		<Point X = "344" Y = "-131" T = "0" Pressure = "0" />
		<Point X = "345" Y = "-130" T = "0" Pressure = "0" />
		<Point X = "345" Y = "-128" T = "0" Pressure = "0" />
		<Point X = "345" Y = "-126" T = "0" Pressure = "0" />
		<Point X = "345" Y = "-125" T = "0" Pressure = "0" />
		<Point X = "345" Y = "-123" T = "0" Pressure = "0" />
		<Point X = "345" Y = "-121" T = "0" Pressure = "0" />
		<Point X = "345" Y = "-120" T = "0" Pressure = "0" />
		<Point X = "345" Y = "-118" T = "0" Pressure = "0" />
		<Point X = "345" Y = "-116" T = "0" Pressure = "0" />
		<Point X = "345" Y = "-115" T = "0" Pressure = "0" />
		<Point X = "345" Y = "-113" T = "0" Pressure = "0" />
		<Point X = "345" Y = "-112" T = "0" Pressure = "0" />
		<Point X = "345" Y = "-111" T = "0" Pressure = "0" />
		<Point X = "345" Y = "-109" T = "0" Pressure = "0" />
		<Point X = "345" Y = "-108" T = "0" Pressure = "0" />
		<Point X = "345" Y = "-107" T = "0" Pressure = "0" />
		<Point X = "344" Y = "-105" T = "0" Pressure = "0" />
		<Point X = "344" Y = "-105" T = "0" Pressure = "0" />
		<Point X = "344" Y = "-103" T = "0" Pressure = "0" />
		<Point X = "343" Y = "-102" T = "0" Pressure = "0" />
		<Point X = "342" Y = "-101" T = "0" Pressure = "0" />
		<Point X = "342" Y = "-100" T = "0" Pressure = "0" />
		<Point X = "342" Y = "-99" T = "0" Pressure = "0" />
		<Point X = "341" Y = "-97" T = "0" Pressure = "0" />
		<Point X = "341" Y = "-96" T = "0" Pressure = "0" />
		<Point X = "340" Y = "-96" T = "0" Pressure = "0" />
		<Point X = "339" Y = "-94" T = "0" Pressure = "0" />
		<Point X = "338" Y = "-93" T = "0" Pressure = "0" />
		<Point X = "338" Y = "-93" T = "0" Pressure = "0" />
		<Point X = "337" Y = "-92" T = "0" Pressure = "0" />
		<Point X = "337" Y = "-91" T = "0" Pressure = "0" />
		<Point X = "336" Y = "-89" T = "0" Pressure = "0" />
		<Point X = "335" Y = "-89" T = "0" Pressure = "0" />
		<Point X = "334" Y = "-88" T = "0" Pressure = "0" />
		<Point X = "333" Y = "-87" T = "0" Pressure = "0" />
		<Point X = "332" Y = "-86" T = "0" Pressure = "0" />
		<Point X = "330" Y = "-85" T = "0" Pressure = "0" />
		<Point X = "330" Y = "-84" T = "0" Pressure = "0" />
		<Point X = "329" Y = "-83" T = "0" Pressure = "0" />
		<Point X = "328" Y = "-83" T = "0" Pressure = "0" />
		<Point X = "326" Y = "-82" T = "0" Pressure = "0" />
		<Point X = "325" Y = "-81" T = "0" Pressure = "0" />
		<Point X = "324" Y = "-80" T = "0" Pressure = "0" />
		<Point X = "324" Y = "-79" T = "0" Pressure = "0" />
		<Point X = "322" Y = "-78" T = "0" Pressure = "0" />
		<Point X = "321" Y = "-78" T = "0" Pressure = "0" />
		<Point X = "320" Y = "-77" T = "0" Pressure = "0" />
		<Point X = "319" Y = "-76" T = "0" Pressure = "0" />
		<Point X = "318" Y = "-75" T = "0" Pressure = "0" />
		<Point X = "317" Y = "-75" T = "0" Pressure = "0" />
		<Point X = "315" Y = "-74" T = "0" Pressure = "0" />
		<Point X = "314" Y = "-73" T = "0" Pressure = "0" />
		<Point X = "313" Y = "-72" T = "0" Pressure = "0" />
		<Point X = "312" Y = "-72" T = "0" Pressure = "0" />
		<Point X = "311" Y = "-71" T = "0" Pressure = "0" />
		<Point X = "309" Y = "-71" T = "0" Pressure = "0" />
		<Point X = "308" Y = "-71" T = "0" Pressure = "0" />
		<Point X = "307" Y = "-70" T = "0" Pressure = "0" />
		<Point X = "307" Y = "-70" T = "0" Pressure = "0" />
		<Point X = "304" Y = "-70" T = "0" Pressure = "0" />
		<Point X = "304" Y = "-69" T = "0" Pressure = "0" />
		<Point X = "303" Y = "-69" T = "0" Pressure = "0" />
		<Point X = "301" Y = "-68" T = "0" Pressure = "0" />
		<Point X = "301" Y = "-68" T = "0" Pressure = "0" />
		<Point X = "300" Y = "-68" T = "0" Pressure = "0" />
		<Point X = "299" Y = "-68" T = "0" Pressure = "0" />
		<Point X = "298" Y = "-67" T = "0" Pressure = "0" />
		<Point X = "297" Y = "-67" T = "0" Pressure = "0" />
		<Point X = "296" Y = "-67" T = "0" Pressure = "0" />
		<Point X = "295" Y = "-67" T = "0" Pressure = "0" />
		<Point X = "294" Y = "-66" T = "0" Pressure = "0" />
		<Point X = "293" Y = "-66" T = "0" Pressure = "0" />
		<Point X = "292" Y = "-66" T = "0" Pressure = "0" />
		<Point X = "291" Y = "-66" T = "0" Pressure = "0" />
		<Point X = "290" Y = "-66" T = "0" Pressure = "0" />
		<Point X = "290" Y = "-66" T = "0" Pressure = "0" />
		<Point X = "288" Y = "-66" T = "0" Pressure = "0" />
		<Point X = "288" Y = "-66" T = "0" Pressure = "0" />
		<Point X = "287" Y = "-66" T = "0" Pressure = "0" />
		<Point X = "286" Y = "-66" T = "0" Pressure = "0" />
		<Point X = "284" Y = "-65" T = "0" Pressure = "0" />
		<Point X = "283" Y = "-65" T = "0" Pressure = "0" />
		<Point X = "282" Y = "-65" T = "0" Pressure = "0" />
		<Point X = "281" Y = "-65" T = "0" Pressure = "0" />
		<Point X = "280" Y = "-65" T = "0" Pressure = "0" />
		<Point X = "279" Y = "-65" T = "0" Pressure = "0" />
		<Point X = "278" Y = "-65" T = "0" Pressure = "0" />
		<Point X = "277" Y = "-65" T = "0" Pressure = "0" />
		<Point X = "276" Y = "-65" T = "0" Pressure = "0" />
		<Point X = "275" Y = "-65" T = "0" Pressure = "0" />
		<Point X = "274" Y = "-65" T = "0" Pressure = "0" />
		<Point X = "274" Y = "-65" T = "0" Pressure = "0" />
		<Point X = "272" Y = "-65" T = "0" Pressure = "0" />
		<Point X = "272" Y = "-65" T = "0" Pressure = "0" />
		<Point X = "271" Y = "-65" T = "0" Pressure = "0" />
		<Point X = "270" Y = "-65" T = "0" Pressure = "0" />
		<Point X = "270" Y = "-65" T = "0" Pressure = "0" />
		<Point X = "270" Y = "-65" T = "0" Pressure = "0" />
		<Point X = "268" Y = "-65" T = "0" Pressure = "0" />
		<Point X = "268" Y = "-65" T = "0" Pressure = "0" />
		<Point X = "267" Y = "-65" T = "0" Pressure = "0" />
		<Point X = "267" Y = "-65" T = "0" Pressure = "0" />
		<Point X = "266" Y = "-65" T = "0" Pressure = "0" />
		<Point X = "265" Y = "-65" T = "0" Pressure = "0" />
		<Point X = "264" Y = "-65" T = "0" Pressure = "0" />
		<Point X = "263" Y = "-65" T = "0" Pressure = "0" />
		<Point X = "262" Y = "-65" T = "0" Pressure = "0" />
		<Point X = "262" Y = "-66" T = "0" Pressure = "0" />
		<Point X = "260" Y = "-66" T = "0" Pressure = "0" />
		<Point X = "260" Y = "-66" T = "0" Pressure = "0" />
		<Point X = "259" Y = "-66" T = "0" Pressure = "0" />
		<Point X = "258" Y = "-66" T = "0" Pressure = "0" />
		<Point X = "258" Y = "-66" T = "0" Pressure = "0" />
		<Point X = "257" Y = "-66" T = "0" Pressure = "0" />
		<Point X = "257" Y = "-66" T = "0" Pressure = "0" />
		<Point X = "256" Y = "-66" T = "0" Pressure = "0" />
		<Point X = "255" Y = "-66" T = "0" Pressure = "0" />
		<Point X = "255" Y = "-66" T = "0" Pressure = "0" />
		<Point X = "254" Y = "-66" T = "0" Pressure = "0" />
		<Point X = "254" Y = "-66" T = "0" Pressure = "0" />
		<Point X = "253" Y = "-66" T = "0" Pressure = "0" />
		<Point X = "253" Y = "-66" T = "0" Pressure = "0" />
		<Point X = "252" Y = "-66" T = "0" Pressure = "0" />
		<Point X = "251" Y = "-66" T = "0" Pressure = "0" />
		<Point X = "251" Y = "-66" T = "0" Pressure = "0" />
		<Point X = "250" Y = "-66" T = "0" Pressure = "0" />
		<Point X = "250" Y = "-66" T = "0" Pressure = "0" />
		<Point X = "249" Y = "-66" T = "0" Pressure = "0" />
		<Point X = "249" Y = "-66" T = "0" Pressure = "0" />
		<Point X = "249" Y = "-66" T = "0" Pressure = "0" />
		<Point X = "248" Y = "-66" T = "0" Pressure = "0" />
		<Point X = "247" Y = "-66" T = "0" Pressure = "0" />
		<Point X = "247" Y = "-67" T = "0" Pressure = "0" />
		<Point X = "246" Y = "-67" T = "0" Pressure = "0" />
		<Point X = "246" Y = "-67" T = "0" Pressure = "0" />
		<Point X = "245" Y = "-67" T = "0" Pressure = "0" />
		<Point X = "245" Y = "-67" T = "0" Pressure = "0" />
		<Point X = "245" Y = "-67" T = "0" Pressure = "0" />
		<Point X = "244" Y = "-67" T = "0" Pressure = "0" />
		<Point X = "244" Y = "-67" T = "0" Pressure = "0" />
		<Point X = "243" Y = "-67" T = "0" Pressure = "0" />
		<Point X = "243" Y = "-67" T = "0" Pressure = "0" />
		<Point X = "243" Y = "-67" T = "0" Pressure = "0" />
		<Point X = "242" Y = "-67" T = "0" Pressure = "0" />
		<Point X = "242" Y = "-68" T = "0" Pressure = "0" />
		<Point X = "242" Y = "-68" T = "0" Pressure = "0" />
		<Point X = "241" Y = "-68" T = "0" Pressure = "0" />
		<Point X = "241" Y = "-68" T = "0" Pressure = "0" />
		<Point X = "241" Y = "-68" T = "0" Pressure = "0" />
		<Point X = "241" Y = "-69" T = "0" Pressure = "0" />
		<Point X = "240" Y = "-69" T = "0" Pressure = "0" />
		<Point X = "239" Y = "-69" T = "0" Pressure = "0" />
		<Point X = "239" Y = "-69" T = "0" Pressure = "0" />
		<Point X = "239" Y = "-69" T = "0" Pressure = "0" />
		<Point X = "239" Y = "-69" T = "0" Pressure = "0" />
		<Point X = "238" Y = "-69" T = "0" Pressure = "0" />
		<Point X = "238" Y = "-70" T = "0" Pressure = "0" />
		<Point X = "238" Y = "-70" T = "0" Pressure = "0" />
		<Point X = "237" Y = "-70" T = "0" Pressure = "0" />
		<Point X = "237" Y = "-70" T = "0" Pressure = "0" />
		<Point X = "237" Y = "-70" T = "0" Pressure = "0" />
		<Point X = "236" Y = "-70" T = "0" Pressure = "0" />
		<Point X = "235" Y = "-71" T = "0" Pressure = "0" />
		<Point X = "235" Y = "-71" T = "0" Pressure = "0" />
		<Point X = "234" Y = "-71" T = "0" Pressure = "0" />
		<Point X = "234" Y = "-71" T = "0" Pressure = "0" />
		<Point X = "233" Y = "-72" T = "0" Pressure = "0" />
		<Point X = "233" Y = "-73" T = "0" Pressure = "0" />
		<Point X = "232" Y = "-73" T = "0" Pressure = "0" />
		<Point X = "231" Y = "-73" T = "0" Pressure = "0" />
		<Point X = "231" Y = "-73" T = "0" Pressure = "0" />
		<Point X = "230" Y = "-74" T = "0" Pressure = "0" />
		<Point X = "230" Y = "-74" T = "0" Pressure = "0" />
		<Point X = "229" Y = "-74" T = "0" Pressure = "0" />
		<Point X = "228" Y = "-74" T = "0" Pressure = "0" />
		<Point X = "227" Y = "-75" T = "0" Pressure = "0" />
		<Point X = "226" Y = "-75" T = "0" Pressure = "0" />
		<Point X = "225" Y = "-75" T = "0" Pressure = "0" />
		<Point X = "225" Y = "-76" T = "0" Pressure = "0" />
		<Point X = "224" Y = "-77" T = "0" Pressure = "0" />
		<Point X = "223" Y = "-77" T = "0" Pressure = "0" />
		<Point X = "222" Y = "-77" T = "0" Pressure = "0" />
		<Point X = "222" Y = "-77" T = "0" Pressure = "0" />
		<Point X = "221" Y = "-77" T = "0" Pressure = "0" />
		<Point X = "221" Y = "-77" T = "0" Pressure = "0" />
		<Point X = "220" Y = "-78" T = "0" Pressure = "0" />
		<Point X = "220" Y = "-78" T = "0" Pressure = "0" />
		<Point X = "220" Y = "-78" T = "0" Pressure = "0" />
		<Point X = "219" Y = "-78" T = "0" Pressure = "0" />
		<Point X = "219" Y = "-78" T = "0" Pressure = "0" />
		<Point X = "219" Y = "-78" T = "0" Pressure = "0" />
		<Point X = "219" Y = "-78" T = "0" Pressure = "0" />
		<Point X = "218" Y = "-78" T = "0" Pressure = "0" />
		<Point X = "218" Y = "-78" T = "0" Pressure = "0" />
		<Point X = "218" Y = "-78" T = "0" Pressure = "0" />
		<Point X = "218" Y = "-78" T = "0" Pressure = "0" />
		<Point X = "218" Y = "-78" T = "0" Pressure = "0" />
		<Point X = "218" Y = "-78" T = "0" Pressure = "0" />
		<Point X = "218" Y = "-78" T = "0" Pressure = "0" />
		<Point X = "218" Y = "-78" T = "0" Pressure = "0" />
		<Point X = "218" Y = "-78" T = "0" Pressure = "0" />
		<Point X = "218" Y = "-78" T = "0" Pressure = "0" />
		<Point X = "218" Y = "-78" T = "0" Pressure = "0" />
		<Point X = "218" Y = "-78" T = "0" Pressure = "0" />
		<Point X = "218" Y = "-78" T = "0" Pressure = "0" />
		<Point X = "218" Y = "-78" T = "0" Pressure = "0" />
		<Point X = "218" Y = "-78" T = "0" Pressure = "0" />
		<Point X = "218" Y = "-78" T = "0" Pressure = "0" />
		<Point X = "218" Y = "-78" T = "0" Pressure = "0" />
		<Point X = "217" Y = "-78" T = "0" Pressure = "0" />
		<Point X = "217" Y = "-79" T = "0" Pressure = "0" />
		<Point X = "217" Y = "-79" T = "0" Pressure = "0" />
		<Point X = "217" Y = "-79" T = "0" Pressure = "0" />
		<Point X = "217" Y = "-79" T = "0" Pressure = "0" />
		<Point X = "217" Y = "-79" T = "0" Pressure = "0" />
		<Point X = "217" Y = "-79" T = "0" Pressure = "0" />
		<Point X = "217" Y = "-79" T = "0" Pressure = "0" />
		<Point X = "217" Y = "-79" T = "0" Pressure = "0" />
		<Point X = "217" Y = "-79" T = "0" Pressure = "0" />
	</Stroke>
</Gesture>
